---
layout: post
category:
    - backend
    - java
date: 2021-05-19 20:46
title: ìë°” ë¦¬í„°ëŸ´(literal) í‘œê¸°ë²•ê³¼ String
description: >
    ìë°”ì—ì„œ ë¬¸ìì—´ì„ ë‹´ë‹¹í•˜ëŠ”`String`ì— ëŒ€í•œ íƒêµ¬
image: /assets/img/backend/java.png
related_posts:
    - _posts/backend/java/2021-01-17-dto-vo.md
    - _posts/backend/java/2021-01-16-java-jvm.md
---

* toc
{:toc}
  
&nbsp;  

# ğŸ“• ë¦¬í„°ëŸ´(literal)

---

> ì»´í“¨í„° ê³¼í•™ ë¶„ì•¼ì—ì„œ ë¦¬í„°ëŸ´(literal) ì´ë€ ì†ŒìŠ¤ ì½”ë“œì˜ ê³ ì •ëœ ê°’ì„ ëŒ€í‘œí•˜ëŠ” ìš©ì–´ë‹¤. ê±°ì˜ ëª¨ë“  í”„ë¡œê·¸ë˜ë° ì–¸ì–´ëŠ” ì •ìˆ˜, ë¶€ë™ì†Œìˆ˜ì , ìˆ«ì, ë¬¸ìì—´, ë¶ˆë¦° ìë£Œí˜•ê³¼ ê°™ì€ ìš©ì–´ë¥¼ ê°€ì§€ê³  ìˆë‹¤. ì–´ë–¤ ì–¸ì–´ëŠ” ì—´ê±° íƒ€ì…ì´ë‚˜, ë°°ì—´, ìë£Œí˜•, ê°ì²´ì™€ ê°™ì€ ìš©ì–´ë„ ìˆë‹¤. ë¦¬í„°ëŸ´ê³¼ ëŒ€ì¡°ì ìœ¼ë¡œ, ê³ ì •ëœ ê°’ì„ ê°€ì§ˆ ìˆ˜ ìˆëŠ” ë³€ìˆ˜ë‚˜ ë³€ê²½ë˜ì§€ ì•ŠëŠ” ìƒìˆ˜ê°€ ìˆë‹¤. ë‹¤ìŒì˜ ì˜ˆì œì™€ ê°™ì´, ë¦¬í„°ëŸ´ì€ ë³€ìˆ˜ ì´ˆê¸°í™”ì— ì¢…ì¢… ì‚¬ìš©ëœë‹¤.

&nbsp;  

```java
int i = 1;
String s = "ë´„ì‹¹";
```

{: style="text-align: right" }
_ğŸ“œ ì¶œì²˜ - ìœ„ì¹˜ë°±ê³¼_

&nbsp;  

ìë°”ë¥¼ ê³µë¶€í•˜ë‹¤ ë³´ë©´ ì±…ì—ì„œ, ê°•ì˜ì—ì„œ, ì£¼ë³€ ì‚¬ëŒì— ì˜í•´ì„œ

ë¦¬í„°ëŸ´, ë¦¬í„°ëŸ´ í‘œê¸°ë²•ì´ë¼ëŠ” ìš©ì–´ë¥¼ ì¢…ì¢… ì“°ê³¤ í•œë‹¤.

ìë°”ì˜ ì¸ìŠ¤í„´ìŠ¤ê°€ ë­”ì§€ ì•Œë©´ ì•„ì£¼ ì‰½ê²Œ ì´í•´í•  ìˆ˜ ìˆëŠ” ë‚´ìš©ì´ë‹¤.

ë°˜ëŒ€ë¡œ ìë°”ì˜ ì¸ìŠ¤í„´ìŠ¤ê°€ ë­”ì§€ ì•„ì§ ëª¨ë¥¸ë‹¤ë©´ ì ˆëŒ€ ì œëŒ€ë¡œ ì´í•´í•  ìˆ˜ ì—†ëŠ” ë‚´ìš©ì´ê¸°ë„ í•˜ë‹¤.

&nbsp;  

ìë°”ì—ì„œ ë¬¸ìì—´ì„ ë‹´ë‹¹í•˜ëŠ” ê°ì²´ëŠ” `String`ì´ë‹¤.

ë˜í•œ Stringì€ ì•„ì£¼ ëŒ€í‘œì ì¸ `VO(Value Object)`ì´ë‹¤.

VOê°€ ë­”ì§€ ëª¨ë¥¸ë‹¤ë©´ [DTO ì™€ VOì˜ ì°¨ì´](/backend/java/2021-01-17-dto-vo/)ë¥¼ ì°¸ê³ í•˜ê¸° ë°”ë€ë‹¤.

VOëŠ” ê°ì²´ë¥¼ ê°’ìœ¼ë¡œ ì‚¬ìš©í•˜ê¸° ë•Œë¬¸ì— ë¶ˆë³€ì„±ì„ ê°–ëŠ”ë‹¤.

&nbsp;  

VOì˜ ì´ë¦„ì€ 100ì›ì¸ë° ëŸ°íƒ€ì„ì— ì´ ê°’ì´ ë³€ê²½ë˜ì–´ 

ë‚´ë¶€ì ìœ¼ë¡œ 100ì›ì˜ ê°’ì´ 50ì›ìœ¼ë¡œ ë³€ê²½ëë‹¤ê³  ê°€ì •í•´ë³´ì.

ê·¸ëŸ¼ ì´ VOë¥¼ ì‚¬ìš©í•˜ëŠ” ëª¨ë“  ë¡œì§ì—ì„œ ì—‰ëš±í•œ ê²°ê³¼ë“¤ì´ ë‚˜ì˜¬ ê²ƒì´ë‹¤.

100ì›ì€ ì–´ë–¤ ìƒí™©ì´ë”ë¼ë„ 100ì›ì˜ ê°€ì¹˜ë¥¼ í•´ì•¼ë§Œ í•œë‹¤.

ë”°ë¼ì„œ VOëŠ” ë¶ˆë³€í•´ì•¼í•œë‹¤.

&nbsp;  

VOì˜ ê³µí†µì ì€ `ìˆ˜ì •ì(Setter)`ê°€ ì—†ê±°ë‚˜, `final`ë¡œ ì„ ì–¸ë˜ì–´ ìˆì–´

ì•„ì˜ˆ ê°’ì„ ìˆ˜ì •í•˜ì§€ ëª»í•˜ê±°ë‚˜ ê°’ì„ ìˆ˜ì •í•˜ë ¤ê³  ë“¤ë©´ `ì—ëŸ¬`ê°€ ë°œìƒí•œë‹¤ëŠ” ê²ƒì´ë‹¤.

String ê°ì²´ë¥¼ ì„ ì–¸í•˜ëŠ” ë°ëŠ” ì—¬ëŸ¬ ê°€ì§€ ë°©ë²•ì´ ìˆë‹¤.

&nbsp;  

```java
String str = "abc"; // ë¦¬í„°ëŸ´ í‘œê¸°ë²•

String str = new String(data); // ìƒì„±ì ì‚¬ìš©

char data[] = {'a', 'b', 'c'};
String s = String.valueOf(data); // valueOf ì‚¬ìš©(=ìƒì„±ìì‚¬ìš©)
```

&nbsp;  

valueOf ë©”ì„œë“œ ë˜í•œ ë‚´ë¶€ì ìœ¼ë¡œ ìƒì„±ìë¥¼ ì´ìš©í•œë‹¤.

&nbsp;  

```java
public static String valueOf(char data[]) {
    return new String(data);
}
```

&nbsp;  

`java.lang.String`ì„ ì°¾ì•„ë³´ë©´ ìµœìƒë‹¨ì— ì´ëŸ° ë¬¸êµ¬ê°€ ìˆë‹¤.

> The String class represents character strings. All string literals in Java programs, such as "abc", are implemented as instances of this class. Strings are constant; their values cannot be changed after they are created. String buffers support mutable strings. Because String objects are immutable they can be shared.

&nbsp;  

ì´ê³³ì—ì„œë„ ë¦¬í„°ëŸ´ì´ë¼ëŠ” ìš©ì–´ê°€ ë‚˜ì˜¨ë‹¤.

ì—¬ê¸°ì„œ ê³µì‹ë¬¸ì„œëŠ” ëª‡ ê°€ì§€ ì•„ì£¼ ì¤‘ìš”í•œ ë‚´ìš©ì„ ë§í•˜ê³  ìˆë‹¤.

- `abc`ì™€ ê°™ì€ ìë°” í”„ë¡œê·¸ë¨ì˜ ëª¨ë“  ë¬¸ìì—´ ë¦¬í„°ëŸ´ì€ ì´ í´ë˜ìŠ¤ì˜ ì¸ìŠ¤í„´ìŠ¤ë¡œ êµ¬í˜„ëœë‹¤.
- ë¬¸ìì—´ì€ ìƒì„±ëœ ë’¤ ê°’ì„ ë³€ê²½í•  ìˆ˜ ì—†ë‹¤
- ë¬¸ìì—´ ê°ì²´ëŠ” ë¶ˆë³€í•˜ë¯€ë¡œ ê³µìœ í•  ìˆ˜ ìˆë‹¤

ì´ê²Œ ë¬´ìŠ¨ ë§ì¼ê¹Œ?

&nbsp;  

## ğŸ’¡ ìë°” í”„ë¡œê·¸ë¨ì˜ ëª¨ë“  ë¬¸ìì—´ ë¦¬í„°ëŸ´ì€ ì´ í´ë˜ìŠ¤ì˜ ì¸ìŠ¤í„´ìŠ¤ë¡œ êµ¬í˜„ëœë‹¤. | ë¬¸ìì—´ ê°ì²´ëŠ” ë¶ˆë³€í•˜ë¯€ë¡œ ê³µìœ í•  ìˆ˜ ìˆë‹¤.

---

ìë°”ì—ì„œëŠ” ê°ì²´ì˜ ì¸ìŠ¤í„´ìŠ¤ë¥¼ ìƒì„±í•˜ê¸° ìœ„í•´ ìƒì„±ì(new)ë¥¼ ì´ìš©í•˜ëŠ”ë°,

ì´ ë¦¬í„°ëŸ´ í‘œê¸°ë²•ì„ ì‚¬ìš©í•  ìˆ˜ ìˆëŠ” String í´ë˜ìŠ¤ëŠ” ì˜ˆì™¸ê°€ ëœë‹¤. **(ì´ì™¸ì— ëª‡ ê°€ì§€ ë” ìˆë‹¤)**

&nbsp;  

```java
String s1 = "123";
String s2 = "123";

System.out.println("s1 == s2 ? " + (s1 == s2));
```

&nbsp;  

Stringì€ Objectì´ë¯€ë¡œ equals ë©”ì„œë“œë¡œ ë¹„êµí•˜ëŠ” ê²Œ ì •ì„ì´ë‹¤.

í•˜ì§€ë§Œ ì´ë ‡ê²Œ s1ê³¼ s2ë¥¼ ë¦¬í„°ëŸ´ í‘œê¸°ë²•ìœ¼ë¡œ ì„ ì–¸í•˜ê³  ë™ì¼ ë¹„êµ ì—°ì‚°(==)ì„ ìˆ˜í–‰í•˜ë©´ ì–´ë–¤ ê²°ê³¼ê°€ ë‚˜ì˜¬ê¹Œ?

&nbsp;  

```java
s1 == s2 // true
```

&nbsp;  

trueê°€ ë‚˜ì˜¤ê²Œ ëœë‹¤.

Objectë¼ë¦¬ ë™ì¼ ë¹„êµ ì—°ì‚°ì„ í–ˆëŠ”ë° trueë¼ëŠ” ê²°ê³¼ê°€ ë‚˜ì˜¤ëŠ” ê²ƒë¶€í„°

ë‘ ê°ì²´ì˜ ì£¼ì†Œ ê°’ì´ ê°™ë‹¤ëŠ” ë§ê³¼ ì¼ë§¥ìƒí†µí•˜ë‚˜, ì•„ì§ ì˜ ì´í•´ê°€ ë˜ì§€ ì•ŠëŠ”ë‹¤.

ì§ì ‘ ì£¼ì†Œ ê°’ì„ ì¶œë ¥í•´ë³´ì.

&nbsp;  

```java
System.out.println("System.identityHashCode(s1) = " + System.identityHashCode(s1));
System.out.println("System.identityHashCode(s2) = " + System.identityHashCode(s2));


System.identityHashCode(s1) = 1626877848
System.identityHashCode(s2) = 1626877848
```

&nbsp;  

ë³¼ ê²ƒë„ ì—†ì´ ê°™ë‹¤.

ê·¸ë ‡ë‹¤ë©´ ë¦¬í„°ëŸ´ í‘œê¸°ë²•ì´ ì•„ë‹Œ ìƒì„±ìë¥¼ ì‚¬ìš©í•œë‹¤ë©´?

&nbsp;  

```java
String s1 = "123";
String s2 = new String("123");
    
System.out.println("s1 == s2 ? " + (s1 == s2)); // false
```

&nbsp;  

ì´ì™€ ê°™ì´ falseê°€ ì¶œë ¥ëœë‹¤.

ìƒì„±ìë¡œ ìƒì„±í•˜ëŠ” String ê°ì²´ëŠ” í™ ë©”ëª¨ë¦¬ì— ìƒì„±ë˜ê¸° ë•Œë¬¸ì—,

ë¦¬í„°ëŸ´ í‘œê¸°ë²•ìœ¼ë¡œ ì‘ì„±í•œ s1ê³¼ ë‹¤ë¥¸ ê°ì²´ê°€ ëœë‹¤.

&nbsp;  

```java
String str = "abc"; // ë¦¬í„°ëŸ´ í‘œê¸°ë²•
```

&nbsp;  

ë¦¬í„°ëŸ´ í‘œê¸°ë²•ìœ¼ë¡œ ì„ ì–¸í•œ ê²½ìš° ìƒì„±ìë¥¼ ì‚¬ìš©í•˜ì§€ ì•Šê³ ë„ ì¸ìŠ¤í„´ìŠ¤ê°€ ìƒì„±ë˜ë©° ì´ ì¸ìŠ¤í„´ìŠ¤ëŠ” ì‹±ê¸€í†¤ì´ ëœë‹¤.

ë”°ë¼ì„œ í•œë²ˆ ë¦¬í„°ëŸ´ í‘œê¸°ë²•ìœ¼ë¡œ ìƒì„±í•œ ê°ì²´ëŠ” ë‹¨ í•œ ë²ˆë§Œ ìƒì„±ë˜ë©°,

ì—¬ëŸ¬ í´ë˜ìŠ¤ì—ì„œ ê°™ì´ ì •ì˜í•˜ë”ë¼ë„ ì´ ê°ì²´ëŠ” ëª¨ë‘ ë™ì¼í•œ ì¸ìŠ¤í„´ìŠ¤(ì‹±ê¸€í†¤)ì´ë‹¤.

&nbsp;  

```java
public class Test1 {
    
    String s = "abc";
}

public class Test2 {
    
    String s = "abc";
}


public class StringTest {
    
    public static void main(String[] args) {
        Test1 test1 = new Test1();
        Test2 test2 = new Test2();
    
        System.out.println(test1.s == test2.s); // true
    }
    
}
```

&nbsp;  

Stringì€ ì—¬íƒ€ Objectì™€ í¬ê²Œ ë‹¤ë¥¼ ê²Œ ì—†ì§€ë§Œ, ì´ ë¦¬í„°ëŸ´ í‘œê¸°ë²•ë§Œí¼ì€ êµ‰ì¥íˆ ì‹ ê¸°í•˜ê²Œ ë™ì‘í•œë‹¤.

Stringì„ í˜¸ì¶œí•˜ê±°ë‚˜ ë¦¬í„°ëŸ´ í‘œê¸°ë²•ìœ¼ë¡œ ì„ ì–¸í•  ê²½ìš° Stringì— ì •ì˜ëœ `intern`ì´ ì‹¤í–‰ëœë‹¤.

&nbsp;  

```java
public native String intern();
```

&nbsp;  

ì‹œê·¸ë‹ˆì²˜ì— `native`ë¼ëŠ” í‚¤ì›Œë“œê°€ ë“¤ì–´ê°€ ìˆëŠ”ë°,

ë‚˜ëŠ” ìë°”ë¥¼ ê³µë¶€í•  ë•Œ native í‚¤ì›Œë“œì— ëŒ€í•´ 

ìë°” ì™¸ì˜ ì–¸ì–´ë¡œ ì‘ì„±ëœ ì½”ë“œë¥¼ ìë°”ì—ì„œ ì‚¬ìš©í•˜ê³ ì í•  ë•Œ ì‚¬ìš©ë˜ëŠ” í‚¤ì›Œë“œë¼ê³  ë°°ì› ì—ˆë‹¤.

ì¶”ì í•´ë³´ë‹ˆ Cê³„ì—´ ì–¸ì–´ë¡œ ë­”ê°€ ë§ì´ ì í˜€ìˆì—ˆëŠ”ë°

ì´ì¯¤ ë˜ë‹ˆ ë„ˆë¬´ ë©€ë¦¬ ë‚˜ê°€ëŠ” ê²ƒ ê°™ê¸°ë„ í•˜ê³ , ëŠ¥ë ¥ ë°–ì¸ ê²ƒ ê°™ê¸°ë„ í•˜ì—¬ ì¼ë‹¨ ë³´ë¥˜í•˜ê³ 

internì˜ Docsë¥¼ ì²¨ë¶€í•œë‹¤.

&nbsp;  

> Returns a canonical representation for the string object. A pool of strings, initially empty, is maintained privately by the class String. When the intern method is invoked, if the pool already contains a string equal to this String object as determined by the equals(Object) method, then the string from the pool is returned. Otherwise, this String object is added to the pool and a reference to this String object is returned. It follows that for any two strings s and t, s.intern() == t.intern() is true if and only if s.equals(t) is true. All literal strings and string-valued constant expressions are interned. String literals are defined in section 3.10.5 of the The Javaâ„¢ Language Specification.

&nbsp;  

ì¦‰ ë¦¬í„°ëŸ´ í‘œê¸°ë²•ìœ¼ë¡œ Stringì„ ì„ ì–¸í•˜ê±°ë‚˜, Stringì„ í˜¸ì¶œí–ˆì„ ë•Œ

JVM ë¬¸ìì—´ í’€ì— í•´ë‹¹ ë¬¸ìì—´ì´ ì¡´ì¬í•˜ë©´ í•´ë‹¹ ë¬¸ìì—´ì„ ë°”ë¡œ ë°˜í™˜í•´ì£¼ê³ ,

ë§Œì•½ ë¬¸ìì—´ í’€ì— í•´ë‹¹ ë¬¸ìì—´ì´ ì—†ë‹¤ë©´ ë¬¸ìì—´ì„ í’€ì— ë“±ë¡í•˜ê³  ë“±ë¡ëœ ë¬¸ìì—´ì„ ë°˜í™˜í•´ì¤€ë‹¤ê³  í•œë‹¤.

ë¦¬í„°ëŸ´ í‘œê¸°ë²•ìœ¼ë¡œ String ê°ì²´ë¥¼ ì„ ì–¸í•˜ê³  ìë°” ì—­ì–´ì…ˆë¸”ëŸ¬ë¥¼ ì´ìš©í•´ ì½”ë“œë¥¼ ëœ¯ì–´ë´¤ë‹¤.

&nbsp;  

```shell
javap -verbose StringTest
Warning: Binary file StringTest contains DataStructure.StringTest
Classfile /mnt/d/development/JavaPractice/out/production/JavaPractice/DataStructure/StringTest.class
  Last modified May 19, 2021; size 527 bytes
  MD5 checksum de12796c5d61a5bdd6c8e440e84fbb6e
  Compiled from "StringTest.java"
public class DataStructure.StringTest
  minor version: 0
  major version: 55
  flags: ACC_PUBLIC, ACC_SUPER
Constant pool:
   #1 = Methodref          #6.#22         // java/lang/Object."<init>":()V
   #2 = Class              #23            // java/lang/String
   #3 = String             #24            // ì•ˆë…•í•˜ì„¸ìš”
   #4 = Methodref          #2.#25         // java/lang/String."<init>":(Ljava/lang/String;)V
   #5 = Class              #26            // DataStructure/StringTest
   #6 = Class              #27            // java/lang/Object
   #7 = Utf8               <init>
   #8 = Utf8               ()V
   #9 = Utf8               Code
  #10 = Utf8               LineNumberTable
  #11 = Utf8               LocalVariableTable
  #12 = Utf8               this
  #13 = Utf8               LDataStructure/StringTest;
  #14 = Utf8               main
  #15 = Utf8               ([Ljava/lang/String;)V
  #16 = Utf8               args
  #17 = Utf8               [Ljava/lang/String;
  #18 = Utf8               s
  #19 = Utf8               Ljava/lang/String;
  #20 = Utf8               SourceFile
  #21 = Utf8               StringTest.java
  #22 = NameAndType        #7:#8          // "<init>":()V
  #23 = Utf8               java/lang/String
  #24 = Utf8               ì•ˆë…•í•˜ì„¸ìš”
  #25 = NameAndType        #7:#28         // "<init>":(Ljava/lang/String;)V
  #26 = Utf8               DataStructure/StringTest
  #27 = Utf8               java/lang/Object
  #28 = Utf8               (Ljava/lang/String;)V
{
  public DataStructure.StringTest();
    descriptor: ()V
    flags: ACC_PUBLIC
    Code:
      stack=1, locals=1, args_size=1
         0: aload_0
         1: invokespecial #1                  // Method java/lang/Object."<init>":()V
         4: return
      LineNumberTable:
        line 3: 0
      LocalVariableTable:
        Start  Length  Slot  Name   Signature
            0       5     0  this   LDataStructure/StringTest;

  public static void main(java.lang.String[]);
    descriptor: ([Ljava/lang/String;)V
    flags: ACC_PUBLIC, ACC_STATIC
    Code:
      stack=3, locals=2, args_size=1
         0: new           #2                  // class java/lang/String
         3: dup
         4: ldc           #3                  // String ì•ˆë…•í•˜ì„¸ìš”
         6: invokespecial #4                  // Method java/lang/String."<init>":(Ljava/lang/String;)V
         9: astore_1
        10: return
      LineNumberTable:
        line 6: 0
        line 9: 10
      LocalVariableTable:
        Start  Length  Slot  Name   Signature
            0      11     0  args   [Ljava/lang/String;
           10       1     1     s   Ljava/lang/String;
}
SourceFile: "StringTest.java"
```

&nbsp;  

JVM ìƒìˆ˜í’€ë¡œ ë³´ì´ëŠ” `Constant pool`ì´ë¼ê³  ì í˜€ìˆëŠ” ë¶€ë¶„ì—

ë‚´ê°€ ë¦¬í„°ëŸ´ í‘œê¸°ë²•ìœ¼ë¡œ ì„ ì–¸í•œ ëª¨ë“  ë¬¸ìì—´ì´ ë“¤ì–´ìˆìŒì„ í™•ì¸í•  ìˆ˜ ìˆì—ˆë‹¤.

ì¦‰ ì´ Constant poolì—ì„œ ë¬¸ìì—´ì„ ê²€ìƒ‰í•˜ê±°ë‚˜ ë“±ë¡í•˜ê³  ë°˜í™˜í•œë‹¤ëŠ” ëœ»ìœ¼ë¡œ ìƒê°ëœë‹¤.

&nbsp;  

## ğŸ’¡ ë¬¸ìì—´ì€ ë¦¬í„°ëŸ´ë¡œ ìƒì„±ëœ ë’¤ ê°’ì„ ë³€ê²½í•  ìˆ˜ ì—†ë‹¤

---

Stringì€ ë¶ˆë³€ ê°ì²´ë‹µê²Œ ì—­ì‹œë‚˜ ìˆ˜ì •ì(Setter)ê°€ ì—†ë‹¤.

ë˜í•œ ë‚´ë¶€ì ìœ¼ë¡œ ì‘ì„±ëœ ì½”ë“œë¥¼ ë³´ë©´

&nbsp;  

```java
public final class String
    implements java.io.Serializable, Comparable<String>, CharSequence {

    @Stable
    private final byte[] value;
    
    ...
    
}
```

&nbsp;  

ì´ì™€ ê°™ì´ `final`ë¡œ ì„ ì–¸ë¼ìˆìŒì„ ì•Œ ìˆ˜ ìˆë‹¤.

ì¦‰ ê°’ì„ ë°”ê¾¸ê³  ì‹¶ì–´ë„ ë°”ê¿€ ìˆ˜ê°€ ì—†ë‹¤.

ê°’ì„ ë°”ê¾¸ê³  ì‹¶ë‹¤ë©´ ì•„ì˜ˆ ìƒˆë¡œìš´ ì¸ìŠ¤í„´ìŠ¤ë¥¼ ë§Œë“¤ì–´ì„œ ì£¼ì†Œë¥¼ ì°¸ì¡°í•´ì•¼ë§Œ í•œë‹¤.

&nbsp;  
